par_run/__init__.py
par_run/cli.py
par_run/executor.py
par_run/web.py
par_run/static/css/style.css
par_run/static/js/app.js
par_run/templates/index.html
par_run-0.5.0.dist-info/METADATA
par_run-0.5.0.dist-info/WHEEL
par_run-0.5.0.dist-info/entry_points.txt
par_run-0.5.0.dist-info/licenses/LICENSE
par_run-0.5.0.dist-info/RECORD
