Metadata-Version: 2.3
Name: par-run
Version: 0.5.0
Summary: Parallel command runner
Project-URL: Homepage, https://github.com/nazq/par-run
Project-URL: Documentation, https://github.com/nazq/par-run
Project-URL: Repository, https://github.com/nazq/par-run
Project-URL: Issues, https://github.com/nazq/par-run/issues
Project-URL: Changelog, https://github.com/nazq/par-run
Author-email: Naz Quadri <naz.quadri@gmail.com>
License-Expression: MIT
License-File: LICENSE
Classifier: Development Status :: 4 - Beta
Classifier: Intended Audience :: Developers
Classifier: License :: OSI Approved :: MIT License
Classifier: Natural Language :: English
Classifier: Programming Language :: Python :: 3
Classifier: Programming Language :: Python :: 3.9
Classifier: Programming Language :: Python :: 3.10
Classifier: Programming Language :: Python :: 3.11
Classifier: Programming Language :: Python :: 3.12
Requires-Python: >=3.9
Requires-Dist: anyio[trio]>=4.3.0
Requires-Dist: exceptiongroup>=1.2.1
Requires-Dist: pydantic>=2.0.0
Requires-Dist: rich>=13.0.0
Requires-Dist: tomlkit>=0.12.4
Requires-Dist: typer>=0.9.0
Provides-Extra: web
Requires-Dist: fastapi>=0.100.0; extra == 'web'
Requires-Dist: jinja2>=3.0.0; extra == 'web'
Requires-Dist: psutil>=5.9.0; extra == 'web'
Requires-Dist: uvicorn[standard]>=0.29.0; extra == 'web'
